codeflash/LICENSE
codeflash/__init__.py
codeflash/either.py
codeflash/main.py
codeflash/tracer.py
codeflash/update_license_version.py
codeflash/version.py
codeflash/api/__init__.py
codeflash/api/aiservice.py
codeflash/api/cfapi.py
codeflash/benchmarking/__init__.py
codeflash/benchmarking/codeflash_trace.py
codeflash/benchmarking/function_ranker.py
codeflash/benchmarking/instrument_codeflash_trace.py
codeflash/benchmarking/pytest_new_process_trace_benchmarks.py
codeflash/benchmarking/replay_test.py
codeflash/benchmarking/trace_benchmarks.py
codeflash/benchmarking/utils.py
codeflash/benchmarking/plugin/__init__.py
codeflash/benchmarking/plugin/plugin.py
codeflash/cli_cmds/__init__.py
codeflash/cli_cmds/cli.py
codeflash/cli_cmds/cli_common.py
codeflash/cli_cmds/cmd_init.py
codeflash/cli_cmds/console.py
codeflash/cli_cmds/console_constants.py
codeflash/cli_cmds/logging_config.py
codeflash/cli_cmds/workflows/codeflash-optimize.yaml
codeflash/code_utils/__init__.py
codeflash/code_utils/checkpoint.py
codeflash/code_utils/code_extractor.py
codeflash/code_utils/code_replacer.py
codeflash/code_utils/code_utils.py
codeflash/code_utils/compat.py
codeflash/code_utils/concolic_utils.py
codeflash/code_utils/config_consts.py
codeflash/code_utils/config_parser.py
codeflash/code_utils/coverage_utils.py
codeflash/code_utils/edit_generated_tests.py
codeflash/code_utils/env_utils.py
codeflash/code_utils/formatter.py
codeflash/code_utils/git_utils.py
codeflash/code_utils/github_utils.py
codeflash/code_utils/instrument_existing_tests.py
codeflash/code_utils/line_profile_utils.py
codeflash/code_utils/shell_utils.py
codeflash/code_utils/static_analysis.py
codeflash/code_utils/tabulate.py
codeflash/code_utils/time_utils.py
codeflash/context/__init__.py
codeflash/context/code_context_extractor.py
codeflash/context/unused_definition_remover.py
codeflash/discovery/__init__.py
codeflash/discovery/discover_unit_tests.py
codeflash/discovery/functions_to_optimize.py
codeflash_ali_dev-0.10.15.dist-info/METADATA
codeflash_ali_dev-0.10.15.dist-info/WHEEL
codeflash_ali_dev-0.10.15.dist-info/entry_points.txt
codeflash_ali_dev-0.10.15.dist-info/RECORD
