Metadata-Version: 2.4
Name: codeflash-ali-dev
Version: 0.10.15
Summary: Client for codeflash.ai - automatic code performance optimization, powered by AI
Project-URL: Homepage, https://codeflash.ai
Author-email: "CodeFlash Inc." <contact@codeflash.ai>
License: BSL-1.1
Keywords: LLM,ai,code,codeflash,machine learning,optimization,performance
Requires-Python: >=3.9
Requires-Dist: click>=8.1.0
Requires-Dist: coverage>=7.6.4
Requires-Dist: crosshair-tool>=0.0.78
Requires-Dist: dill>=0.3.8
Requires-Dist: gitpython>=3.1.31
Requires-Dist: humanize>=4.0.0
Requires-Dist: inquirer>=3.0.0
Requires-Dist: isort>=5.11.0
Requires-Dist: jedi>=0.19.1
Requires-Dist: junitparser>=3.1.0
Requires-Dist: libcst>=1.0.1
Requires-Dist: line-profiler>=4.2.0
Requires-Dist: lxml>=5.3.0
Requires-Dist: parameterized>=0.9.0
Requires-Dist: platformdirs>=4.3.7
Requires-Dist: posthog>=3.0.0
Requires-Dist: pydantic>=1.10.1
Requires-Dist: pygls>=1.3.1
Requires-Dist: pytest!=8.3.4,>=7.0.0
Requires-Dist: pytest-timeout>=2.1.0
Requires-Dist: rich>=13.8.1
Requires-Dist: sentry-sdk<3.0.0,>=1.40.6
Requires-Dist: timeout-decorator>=0.5.0
Requires-Dist: tomlkit>=0.11.7
Requires-Dist: unidiff>=0.7.4
Requires-Dist: unittest-xml-reporting>=3.2.0
